{"losses/adversary_entropy":7.284364,"_step":39091,"charts/learning_rate":4.918033e-07,"Robustness/V_ema":1673.0613,"charts/SPS":746,"losses/adversary_policy_loss":-0.16797228,"losses/critic_value_loss":0.016135463,"_wandb":{"runtime":6698},"losses/explained_variance":0.8378912,"Custom_Metrics/Episodic_Return":394.1009054129672,"Robustness/alpha_clip_count":0,"_timestamp":1.781871306590501e+09,"losses/protagonist_entropy":2.2688475,"global_step":4997120,"Robustness/grad_V_alpha":-320.88324,"Robustness/constraint":-1026.9387,"losses/protagonist_approx_kl":0.00019048553,"charts/episodic_return":394.1009,"losses/protagonist_policy_loss":-0.007703246,"_runtime":6698,"Robustness/alpha_step":0,"Robustness/alpha":0.05}