{"losses/adversary_entropy":8.399936,"losses/critic_value_loss":0.023616616,"charts/SPS":476,"losses/explained_variance":0.35949755,"Robustness/grad_V_alpha":-53.966892,"charts/learning_rate":3.382459e-08,"Custom_Metrics/Episodic_Return":1045.2206077444594,"losses/adversary_policy_loss":-1.2472708,"Robustness/V_ema":1051.4019,"losses/protagonist_entropy":-0.56345016,"_runtime":10491,"Robustness/alpha":0.05,"_wandb":{"runtime":10491},"losses/protagonist_policy_loss":-0.050971396,"Robustness/alpha_step":0,"Robustness/constraint":-1648.5981,"losses/protagonist_approx_kl":4.2513134e-06,"global_step":4997120,"charts/episodic_return":1045.2206,"Robustness/alpha_clip_count":0,"_timestamp":1.7822480708934891e+09,"_step":18035}